{
  "de": {
    "current": false,
    "baseTotal": 12,
    "total": 12,
    "states": {
      "current": 9,
      "missing": 1,
      "outdated": 2,
      "unused": 1
    },
    "keys": {
      "astro-and-rosey-bookshop-starter": "missing",
      "blog": "current",
      "keep-what-you-need-delete-the-rest": "current",
      "github": "current",
      "static:/blog/email-delivery-tips/": "current",
      "cloudcannon": "current",
      "static:/blog/a-test-page/": "current",
      "static:hero-subheading-about-1": "current",
      "static:left-right-text-home-1": "outdated",
      "rss-feed": "current",
      "static:hero-subheading-home-1": "outdated",
      "about": "current",
      "astro-bookshop-starter": "unused"
    }
  },
  "de-de": {
    "current": true,
    "baseTotal": 12,
    "total": 12,
    "states": {
      "current": 12,
      "missing": 0,
      "outdated": 0,
      "unused": 0
    },
    "keys": {
      "static:left-right-text-home-1": "current",
      "static:/blog/a-test-page/": "current",
      "static:/blog/email-delivery-tips/": "current",
      "rss-feed": "current",
      "cloudcannon": "current",
      "static:hero-subheading-about-1": "current",
      "keep-what-you-need-delete-the-rest": "current",
      "blog": "current",
      "about": "current",
      "github": "current",
      "static:hero-subheading-home-1": "current",
      "astro-and-rosey-bookshop-starter": "current"
    }
  },
  "de-de.urls": {
    "current": false,
    "baseTotal": 12,
    "total": 8,
    "states": {
      "outdated": 0,
      "missing": 12,
      "current": 0,
      "unused": 8
    },
    "keys": {
      "blog/email-delivery-tips/index.html": "unused",
      "blog/a-test-page/index.html": "unused",
      "rss-feed": "missing",
      "blog/index.html": "unused",
      "static:hero-subheading-about-1": "missing",
      "about/index.html": "unused",
      "static:hero-subheading-home-1": "missing",
      "tags/Testing/index.html": "unused",
      "tags/email/index.html": "unused",
      "index.html": "unused",
      "static:/blog/a-test-page/": "missing",
      "blog": "missing",
      "github": "missing",
      "keep-what-you-need-delete-the-rest": "missing",
      "about": "missing",
      "astro-and-rosey-bookshop-starter": "missing",
      "cloudcannon": "missing",
      "static:/blog/email-delivery-tips/": "missing",
      "static:left-right-text-home-1": "missing",
      "404.html": "unused"
    }
  },
  "de.urls": {
    "current": false,
    "baseTotal": 12,
    "total": 8,
    "states": {
      "unused": 8,
      "missing": 12,
      "outdated": 0,
      "current": 0
    },
    "keys": {
      "blog": "missing",
      "blog/email-delivery-tips/index.html": "unused",
      "cloudcannon": "missing",
      "astro-and-rosey-bookshop-starter": "missing",
      "404.html": "unused",
      "blog/a-test-page/index.html": "unused",
      "blog/index.html": "unused",
      "index.html": "unused",
      "tags/email/index.html": "unused",
      "tags/Testing/index.html": "unused",
      "about": "missing",
      "static:/blog/a-test-page/": "missing",
      "static:hero-subheading-about-1": "missing",
      "static:left-right-text-home-1": "missing",
      "about/index.html": "unused",
      "rss-feed": "missing",
      "static:/blog/email-delivery-tips/": "missing",
      "static:hero-subheading-home-1": "missing",
      "github": "missing",
      "keep-what-you-need-delete-the-rest": "missing"
    }
  },
  "es": {
    "current": false,
    "baseTotal": 12,
    "total": 12,
    "states": {
      "missing": 1,
      "current": 9,
      "unused": 1,
      "outdated": 2
    },
    "keys": {
      "about": "current",
      "blog": "current",
      "rss-feed": "current",
      "static:hero-subheading-about-1": "current",
      "static:hero-subheading-home-1": "outdated",
      "astro-bookshop-starter": "unused",
      "cloudcannon": "current",
      "keep-what-you-need-delete-the-rest": "current",
      "static:/blog/a-test-page/": "current",
      "static:left-right-text-home-1": "outdated",
      "astro-and-rosey-bookshop-starter": "missing",
      "static:/blog/email-delivery-tips/": "current",
      "github": "current"
    }
  },
  "es-es": {
    "current": true,
    "baseTotal": 12,
    "total": 12,
    "states": {
      "missing": 0,
      "outdated": 0,
      "current": 12,
      "unused": 0
    },
    "keys": {
      "static:left-right-text-home-1": "current",
      "rss-feed": "current",
      "cloudcannon": "current",
      "static:/blog/email-delivery-tips/": "current",
      "blog": "current",
      "keep-what-you-need-delete-the-rest": "current",
      "about": "current",
      "astro-and-rosey-bookshop-starter": "current",
      "static:hero-subheading-about-1": "current",
      "github": "current",
      "static:/blog/a-test-page/": "current",
      "static:hero-subheading-home-1": "current"
    }
  },
  "es-es.urls": {
    "current": false,
    "baseTotal": 12,
    "total": 8,
    "states": {
      "unused": 8,
      "missing": 12,
      "outdated": 0,
      "current": 0
    },
    "keys": {
      "blog": "missing",
      "about/index.html": "unused",
      "rss-feed": "missing",
      "static:hero-subheading-home-1": "missing",
      "tags/Testing/index.html": "unused",
      "about": "missing",
      "static:/blog/a-test-page/": "missing",
      "tags/email/index.html": "unused",
      "github": "missing",
      "blog/index.html": "unused",
      "404.html": "unused",
      "astro-and-rosey-bookshop-starter": "missing",
      "cloudcannon": "missing",
      "blog/a-test-page/index.html": "unused",
      "static:hero-subheading-about-1": "missing",
      "blog/email-delivery-tips/index.html": "unused",
      "index.html": "unused",
      "keep-what-you-need-delete-the-rest": "missing",
      "static:/blog/email-delivery-tips/": "missing",
      "static:left-right-text-home-1": "missing"
    }
  },
  "es.urls": {
    "current": false,
    "baseTotal": 12,
    "total": 8,
    "states": {
      "unused": 8,
      "outdated": 0,
      "current": 0,
      "missing": 12
    },
    "keys": {
      "blog": "missing",
      "blog/email-delivery-tips/index.html": "unused",
      "blog/a-test-page/index.html": "unused",
      "astro-and-rosey-bookshop-starter": "missing",
      "404.html": "unused",
      "keep-what-you-need-delete-the-rest": "missing",
      "github": "missing",
      "about": "missing",
      "static:/blog/email-delivery-tips/": "missing",
      "static:left-right-text-home-1": "missing",
      "about/index.html": "unused",
      "blog/index.html": "unused",
      "rss-feed": "missing",
      "tags/Testing/index.html": "unused",
      "tags/email/index.html": "unused",
      "static:hero-subheading-home-1": "missing",
      "cloudcannon": "missing",
      "index.html": "unused",
      "static:/blog/a-test-page/": "missing",
      "static:hero-subheading-about-1": "missing"
    }
  },
  "fr": {
    "current": false,
    "baseTotal": 12,
    "total": 12,
    "states": {
      "current": 9,
      "outdated": 2,
      "unused": 1,
      "missing": 1
    },
    "keys": {
      "about": "current",
      "astro-and-rosey-bookshop-starter": "missing",
      "blog": "current",
      "cloudcannon": "current",
      "static:hero-subheading-about-1": "current",
      "github": "current",
      "keep-what-you-need-delete-the-rest": "current",
      "static:/blog/email-delivery-tips/": "current",
      "static:hero-subheading-home-1": "outdated",
      "static:left-right-text-home-1": "outdated",
      "rss-feed": "current",
      "astro-bookshop-starter": "unused",
      "static:/blog/a-test-page/": "current"
    }
  },
  "fr-fr": {
    "current": true,
    "baseTotal": 12,
    "total": 12,
    "states": {
      "current": 12,
      "unused": 0,
      "outdated": 0,
      "missing": 0
    },
    "keys": {
      "static:left-right-text-home-1": "current",
      "about": "current",
      "astro-and-rosey-bookshop-starter": "current",
      "blog": "current",
      "cloudcannon": "current",
      "keep-what-you-need-delete-the-rest": "current",
      "static:/blog/a-test-page/": "current",
      "static:/blog/email-delivery-tips/": "current",
      "rss-feed": "current",
      "static:hero-subheading-about-1": "current",
      "static:hero-subheading-home-1": "current",
      "github": "current"
    }
  },
  "fr-fr.urls": {
    "current": false,
    "baseTotal": 12,
    "total": 8,
    "states": {
      "missing": 12,
      "current": 0,
      "unused": 8,
      "outdated": 0
    },
    "keys": {
      "blog/email-delivery-tips/index.html": "unused",
      "cloudcannon": "missing",
      "index.html": "unused",
      "about": "missing",
      "static:/blog/a-test-page/": "missing",
      "about/index.html": "unused",
      "404.html": "unused",
      "rss-feed": "missing",
      "tags/email/index.html": "unused",
      "astro-and-rosey-bookshop-starter": "missing",
      "blog/a-test-page/index.html": "unused",
      "tags/Testing/index.html": "unused",
      "static:left-right-text-home-1": "missing",
      "static:/blog/email-delivery-tips/": "missing",
      "blog": "missing",
      "github": "missing",
      "static:hero-subheading-about-1": "missing",
      "static:hero-subheading-home-1": "missing",
      "blog/index.html": "unused",
      "keep-what-you-need-delete-the-rest": "missing"
    }
  },
  "fr.urls": {
    "current": false,
    "baseTotal": 12,
    "total": 8,
    "states": {
      "current": 0,
      "outdated": 0,
      "missing": 12,
      "unused": 8
    },
    "keys": {
      "keep-what-you-need-delete-the-rest": "missing",
      "github": "missing",
      "blog/email-delivery-tips/index.html": "unused",
      "tags/Testing/index.html": "unused",
      "index.html": "unused",
      "blog/a-test-page/index.html": "unused",
      "blog/index.html": "unused",
      "tags/email/index.html": "unused",
      "cloudcannon": "missing",
      "about/index.html": "unused",
      "404.html": "unused",
      "rss-feed": "missing",
      "static:hero-subheading-about-1": "missing",
      "static:/blog/email-delivery-tips/": "missing",
      "static:/blog/a-test-page/": "missing",
      "about": "missing",
      "static:left-right-text-home-1": "missing",
      "astro-and-rosey-bookshop-starter": "missing",
      "blog": "missing",
      "static:hero-subheading-home-1": "missing"
    }
  },
  "jp": {
    "current": false,
    "baseTotal": 12,
    "total": 12,
    "states": {
      "current": 9,
      "outdated": 2,
      "unused": 1,
      "missing": 1
    },
    "keys": {
      "astro-and-rosey-bookshop-starter": "missing",
      "cloudcannon": "current",
      "static:hero-subheading-about-1": "current",
      "astro-bookshop-starter": "unused",
      "rss-feed": "current",
      "github": "current",
      "keep-what-you-need-delete-the-rest": "current",
      "static:/blog/a-test-page/": "current",
      "static:/blog/email-delivery-tips/": "current",
      "static:hero-subheading-home-1": "outdated",
      "blog": "current",
      "about": "current",
      "static:left-right-text-home-1": "outdated"
    }
  },
  "jp.urls": {
    "current": false,
    "baseTotal": 12,
    "total": 8,
    "states": {
      "current": 0,
      "missing": 12,
      "unused": 8,
      "outdated": 0
    },
    "keys": {
      "static:/blog/email-delivery-tips/": "missing",
      "blog/email-delivery-tips/index.html": "unused",
      "static:hero-subheading-about-1": "missing",
      "index.html": "unused",
      "astro-and-rosey-bookshop-starter": "missing",
      "keep-what-you-need-delete-the-rest": "missing",
      "blog": "missing",
      "blog/a-test-page/index.html": "unused",
      "static:/blog/a-test-page/": "missing",
      "rss-feed": "missing",
      "static:hero-subheading-home-1": "missing",
      "tags/Testing/index.html": "unused",
      "github": "missing",
      "static:left-right-text-home-1": "missing",
      "404.html": "unused",
      "blog/index.html": "unused",
      "about/index.html": "unused",
      "cloudcannon": "missing",
      "about": "missing",
      "tags/email/index.html": "unused"
    }
  }
}